etsy_py/__init__.py
etsy_py/client.py
etsy_py/methods.py
etsy_py/oauth_helper.py
etsy_py/rq.py
etsy_py_dev-0.0.2.dist-info/METADATA
etsy_py_dev-0.0.2.dist-info/WHEEL
etsy_py_dev-0.0.2.dist-info/top_level.txt
etsy_py_dev-0.0.2.dist-info/RECORD
