Metadata-Version: 2.1
Name: etsy-py-dev
Version: 0.0.2
Summary: An auto-updating Etsy Wrapper
Home-page: https://github.com/vyrzdev/etsy-py
Author: vyrzdev
Author-email: ben@vyrz.dev
License: UNKNOWN
Platform: UNKNOWN
Classifier: Programming Language :: Python :: 3
Classifier: License :: OSI Approved :: MIT License
Classifier: Operating System :: OS Independent
Requires-Python: >=3.8
